{
  "products":
  [
    {
      "id": 1,
      "category": "Electronics",
      "images": [
        "https://firebasestorage.googleapis.com/v0/b/webbandongphuc.appspot.com/o/dongphuc1.jpg?alt=media&token=20fbe1d5-b2b2-44e2-a6bc-76677d5520e7"
      ],
      "title": "Đồng Phục Mầm Non 01",
      "brand": "Ao 3 lo",
      "price": 170000,
      "discountedPrice": 1,
      "discountedPercentage": 14
    },
    {
      "id": 2,
      "category": "Books",
      "images": [
        "https://example.com/image3.jpg"
      ],
      "title": "Learn React",
      "brand": "Ao Thun",
      "price": 10000,
      "discountedPrice": 10000,
      "discountedPercentage": 33
    },
    {
      "id": 3,
      "category": "Clothing",
      "images": [
        "https://example.com/image4.jpg",
        "https://example.com/image5.jpg"
      ],
      "title": "T-Shirt",
      "brand": "FashionBrand",
      "price": 90000,
      "discountedPrice": 5000,
      "discountedPercentage": 25
    }
  ]
}

